Metadata-Version: 1.0
Name: arbit
Version: 0.0.11
Summary: Native Arbit client
Home-page: https://github.com/1protocol/arbit-pypi
Author: Tjaden Hess
Author-email: tjaden@1protocol.com
License: GPL3
Platform: UNKNOWN
